{
  "Header": {
    "WolvenKitVersion": "8.10.0",
    "WKitJsonVersion": "0.0.8",
    "GameVersion": 1630,
    "ExportedDateTime": "2023-09-26T03:48:35.7466832Z",
    "DataType": "CR2W",
    "ArchiveFileName": "D:\\2023\\Tháng 9\\CP0277\\TheRedTeam\\source\\archive\\DLC\\6168910715646126648.json"
  },
  "Data": {
    "Version": 195,
    "BuildVersion": 0,
    "RootChunk": {
      "$type": "JsonResource",
      "cookingPlatform": "PLATFORM_PC",
      "root": {
        "HandleId": "0",
        "Data": {
          "$type": "localizationPersistenceSubtitleEntries",
          "entries": [
            {
              "$type": "localizationPersistenceSubtitleEntry",
              "femaleVariant": "OK, so listen. \u0027Fore we left Yuri gave me a list. No power generators there. I look into the truck and what\u0027s there? Generators.",
              "maleVariant": "",
              "stringId": "2960067555311915008"
            },
            {
              "$type": "localizationPersistenceSubtitleEntry",
              "femaleVariant": "And this dumbass thought if he snatched \u0027n\u0027 sold \u0027em, he\u0027d be set for a year. They\u0027re checkin\u0027 to see if he\u0027s cool, he straight up robs \u0027em.",
              "maleVariant": "",
              "stringId": "2960067684714582016"
            },
            {
              "$type": "localizationPersistenceSubtitleEntry",
              "femaleVariant": "Only idiots say no to opportunity, Babs.",
              "maleVariant": "",
              "stringId": "2960068035475836928"
            },
            {
              "$type": "localizationPersistenceSubtitleEntry",
              "femaleVariant": "So what\u0027d you do with this \u0022opportunity\u0022?",
              "maleVariant": "",
              "stringId": "2960069342018310144"
            },
            {
              "$type": "localizationPersistenceSubtitleEntry",
              "femaleVariant": "Uuh.. Well, shit. Sold them to a guy. Said he had a client in India.",
              "maleVariant": "",
              "stringId": "2960069708734697472"
            },
            {
              "$type": "localizationPersistenceSubtitleEntry",
              "femaleVariant": "Prolly bein\u0027 shipped. Can wave \u0027em adios.",
              "maleVariant": "",
              "stringId": "2960070142878715904"
            },
            {
              "$type": "localizationPersistenceSubtitleEntry",
              "femaleVariant": "So the generators – what\u0027d you do?",
              "maleVariant": "",
              "stringId": "3070857826953146372"
            },
            {
              "$type": "localizationPersistenceSubtitleEntry",
              "femaleVariant": "Genius idea…",
              "maleVariant": "",
              "stringId": "3070858804964175872"
            },
            {
              "$type": "localizationPersistenceSubtitleEntry",
              "femaleVariant": "Sheesh, in what world did that seem like a good idea?",
              "maleVariant": "",
              "stringId": "3070859352337625088"
            },
            {
              "$type": "localizationPersistenceSubtitleEntry",
              "femaleVariant": "There\u0027s more, V. See, my little gonklet here sold \u0027em to a dude in India. Prolly on the way there.",
              "maleVariant": "",
              "stringId": "3070871176718135296"
            },
            {
              "$type": "localizationPersistenceSubtitleEntry",
              "femaleVariant": "So we drivin\u0027, right? Boss-man hisself next to me.",
              "maleVariant": "",
              "stringId": "3289142838084145152"
            },
            {
              "$type": "localizationPersistenceSubtitleEntry",
              "femaleVariant": "Motherfuckers…",
              "maleVariant": "",
              "stringId": "3289144460256382984"
            },
            {
              "$type": "localizationPersistenceSubtitleEntry",
              "femaleVariant": "\u003Cmothertongue l=\u0022mex\u0022 m=\u0022mana\u0022 b=\u0022Get me, \u0022 a=\u0022? He saw it all comin\u0027! \u0027S why he went with me!\u0022/\u003E",
              "maleVariant": "\u003Cmothertongue l=\u0022mex\u0022 m=\u0022mano\u0022 b=\u0022Get me, \u0022 a=\u0022? He saw it all comin\u0027! \u0027S why he went with me!\u0022/\u003E",
              "stringId": "3289146022500405256"
            },
            {
              "$type": "localizationPersistenceSubtitleEntry",
              "femaleVariant": "Buckle up, pup. Time to remind these bastards who\u0027s in charge.",
              "maleVariant": "",
              "stringId": "3289146789403725824"
            },
            {
              "$type": "localizationPersistenceSubtitleEntry",
              "femaleVariant": "\u003Ckiroshi l=\u0022mex\u0022 o=\u0022Fue perfecto, maravilloso, cayeron uno detrás de otro.\u0022 t=\u0022Was perfect, beautiful. One after another, droppin\u0027.\u0022 b=\u0022\u0022 a=\u0022\u0022/\u003E",
              "maleVariant": "",
              "stringId": "3289147566507593740"
            },
            {
              "$type": "localizationPersistenceSubtitleEntry",
              "femaleVariant": "Fuck, he was a machine! Like, preee-cise!",
              "maleVariant": "",
              "stringId": "3289148531147182088"
            },
            {
              "$type": "localizationPersistenceSubtitleEntry",
              "femaleVariant": "An\u0027 you know – blam, blam blam! Ratatatatauu! Blastin\u0027 away, yeah?",
              "maleVariant": "",
              "stringId": "3289148899541291016"
            },
            {
              "$type": "localizationPersistenceSubtitleEntry",
              "femaleVariant": "Fuckin\u0027 awesome, preem aim. And he was out for blood!",
              "maleVariant": "",
              "stringId": "3289149823630348292"
            },
            {
              "$type": "localizationPersistenceSubtitleEntry",
              "femaleVariant": "Boss-man got hit. Thinkin\u0027 to myself – this how we fuckin\u0027 die.",
              "maleVariant": "",
              "stringId": "3289151832064430088"
            },
            {
              "$type": "localizationPersistenceSubtitleEntry",
              "femaleVariant": "So many scavs, no way he wasn\u0027t gonna get shot…",
              "maleVariant": "",
              "stringId": "3289153788304592904"
            },
            {
              "$type": "localizationPersistenceSubtitleEntry",
              "femaleVariant": "\u003Cmothertongue l=\u0022mex\u0022 m=\u0022Masacre...\u0022 b=\u0022Slaughtered all of \u0027em, we did. Metallic smell of blood in the air. \u0022 a=\u0022\u0022/\u003E",
              "maleVariant": "",
              "stringId": "3289155680371904512"
            },
            {
              "$type": "localizationPersistenceSubtitleEntry",
              "femaleVariant": "All right. The goods go back to the Sapphire. Just be careful, kid. Yuri and I gotta ask our scav friend some questions.",
              "maleVariant": "",
              "stringId": "3289163022886932480"
            },
            {
              "$type": "localizationPersistenceSubtitleEntry",
              "femaleVariant": "Keep listenin\u0027, V. What this gonk-ass did next is the story ya been waitin\u0027 for.",
              "maleVariant": "",
              "stringId": "3295766048175108096"
            },
            {
              "$type": "localizationPersistenceSubtitleEntry",
              "femaleVariant": "Phew… A\u0027ight… One for the road, then?",
              "maleVariant": "",
              "stringId": "3297029485484126208"
            },
            {
              "$type": "localizationPersistenceSubtitleEntry",
              "femaleVariant": "Well… here\u0027s to dousin\u0027 brush fires and pluggin\u0027 busted dams.",
              "maleVariant": "",
              "stringId": "3297032727060361216"
            },
            {
              "$type": "localizationPersistenceSubtitleEntry",
              "femaleVariant": "[Drink] Here\u0027s to easy outs outta all urgent problems.",
              "maleVariant": "",
              "stringId": "3297033291563347972"
            },
            {
              "$type": "localizationPersistenceSubtitleEntry",
              "femaleVariant": "You have a talent for killing scavs.",
              "maleVariant": "",
              "stringId": "3304057803018416132"
            },
            {
              "$type": "localizationPersistenceSubtitleEntry",
              "femaleVariant": "You survived. Not bad for your first time out.",
              "maleVariant": "",
              "stringId": "3304061271221284864"
            },
            {
              "$type": "localizationPersistenceSubtitleEntry",
              "femaleVariant": "Well… Not half bad, you got somethin\u0027. Weren\u0027t lyin\u0027 about bein\u0027 quick, kiddo. Good work stomping these rats.",
              "maleVariant": "",
              "stringId": "3304112759876431872"
            },
            {
              "$type": "localizationPersistenceSubtitleEntry",
              "femaleVariant": "So, still breathin\u0027, well done. We\u0027ll make a real soldier outta ya yet. All you gotta do is stay with us, be indispensable.",
              "maleVariant": "",
              "stringId": "3304117555324858368"
            },
            {
              "$type": "localizationPersistenceSubtitleEntry",
              "femaleVariant": "They gonna kill him, right? Fuck… an\u0027 me in the bargain…",
              "maleVariant": "",
              "stringId": "3326421513716183040"
            },
            {
              "$type": "localizationPersistenceSubtitleEntry",
              "femaleVariant": "\u003Cmothertongue l=\u0022mex\u0022 m=\u0022¡mierda, esto se sale de madre!\u0022 b=\u0022Suddenly, tires screechin\u0027 an-- and I\u0027m thinkin\u0027 \u0022 a=\u0022\u0022/\u003E",
              "maleVariant": "",
              "stringId": "3327403257139376128"
            },
            {
              "$type": "localizationPersistenceSubtitleEntry",
              "femaleVariant": "Gotta frame Yuri.",
              "maleVariant": "",
              "stringId": "3340906626151780356"
            },
            {
              "$type": "localizationPersistenceSubtitleEntry",
              "femaleVariant": "At this stage… run for the hills, guys.",
              "maleVariant": "",
              "stringId": "3340907870350118912"
            },
            {
              "$type": "localizationPersistenceSubtitleEntry",
              "femaleVariant": "See if I can\u0027t call in some favors. Could work somethin\u0027 out.",
              "maleVariant": "",
              "stringId": "3340908252887420928"
            },
            {
              "$type": "localizationPersistenceSubtitleEntry",
              "femaleVariant": "OK, we frame Yuri. Guy\u0027s on Kurt\u0027s shit list anyway. We do this right, problem\u0027ll solve itself.",
              "maleVariant": "",
              "stringId": "3340914861818679296"
            },
            {
              "$type": "localizationPersistenceSubtitleEntry",
              "femaleVariant": "Fine, l-let\u0027s just please take this convo somewhere else? Underground passageway nearby... talk there. Tomorrow evening, yeah?",
              "maleVariant": "",
              "stringId": "3340915261334523904"
            },
            {
              "$type": "localizationPersistenceSubtitleEntry",
              "femaleVariant": "You two gotta ghost. Yuri\u0027s gonna know who klepped his shit. Can drive ya to Night City if you want.",
              "maleVariant": "",
              "stringId": "3340918840468344832"
            },
            {
              "$type": "localizationPersistenceSubtitleEntry",
              "femaleVariant": "I\u0027m stayin\u0027.",
              "maleVariant": "",
              "stringId": "3340919708320174080"
            },
            {
              "$type": "localizationPersistenceSubtitleEntry",
              "femaleVariant": "Gonna pull strings, call in favors. See if I can\u0027t make some generators appear.",
              "maleVariant": "",
              "stringId": "3340923456132124672"
            },
            {
              "$type": "localizationPersistenceSubtitleEntry",
              "femaleVariant": "Or get us transport, so we can disappear. Out there, past the horizon.",
              "maleVariant": "",
              "stringId": "3340924289372557312"
            },
            {
              "$type": "localizationPersistenceSubtitleEntry",
              "femaleVariant": "Cogs\u0027re grindin\u0027. Gimme a little time.",
              "maleVariant": "",
              "stringId": "3340924667799441408"
            },
            {
              "$type": "localizationPersistenceSubtitleEntry",
              "femaleVariant": "But I did good, deserved a compliment.",
              "maleVariant": "",
              "stringId": "3343309386880987136"
            },
            {
              "$type": "localizationPersistenceSubtitleEntry",
              "femaleVariant": "Dirty fuckin\u0027 rats. Least the kid showed some teeth.",
              "maleVariant": "",
              "stringId": "3343343931923705856"
            },
            {
              "$type": "localizationPersistenceSubtitleEntry",
              "femaleVariant": "C\u0027mon, I see you thinkin\u0027 good. Can you help, sister?",
              "maleVariant": "C\u0027mon, I see you thinkin\u0027 good. Can you help, brother?",
              "stringId": "3344117184602738688"
            },
            {
              "$type": "localizationPersistenceSubtitleEntry",
              "femaleVariant": "\u0027Member, I don\u0027t do charity. And ideas cost scratch.",
              "maleVariant": "",
              "stringId": "3344120234230845444"
            },
            {
              "$type": "localizationPersistenceSubtitleEntry",
              "femaleVariant": "Got a couple ideas…",
              "maleVariant": "",
              "stringId": "3344121476684353536"
            },
            {
              "$type": "localizationPersistenceSubtitleEntry",
              "femaleVariant": "Sure, can help ya. Advice don\u0027t come free, though.",
              "maleVariant": "Sure can help ya. Advice don\u0027t come free, though.",
              "stringId": "3344122712812851200"
            },
            {
              "$type": "localizationPersistenceSubtitleEntry",
              "femaleVariant": "Yeah, yeah, we got scratch, choom.",
              "maleVariant": "",
              "stringId": "3344123542563622912"
            },
            {
              "$type": "localizationPersistenceSubtitleEntry",
              "femaleVariant": "Might have an idea, yeah.",
              "maleVariant": "",
              "stringId": "3344124544012423168"
            },
            {
              "$type": "localizationPersistenceSubtitleEntry",
              "femaleVariant": "W-what? Whatcha mean, Babs?",
              "maleVariant": "",
              "stringId": "3347775973201620992"
            },
            {
              "$type": "localizationPersistenceSubtitleEntry",
              "femaleVariant": "They\u0027ll come for you.",
              "maleVariant": "",
              "stringId": "3347779372450131968"
            },
            {
              "$type": "localizationPersistenceSubtitleEntry",
              "femaleVariant": "Sure? It\u0027s a gamble.",
              "maleVariant": "",
              "stringId": "3347854765299412992"
            },
            {
              "$type": "localizationPersistenceSubtitleEntry",
              "femaleVariant": "Peeps know you two\u0027re tight. They see Paco gone, your ass\u0027ll be on the line, too.",
              "maleVariant": "",
              "stringId": "3347855329215197184"
            },
            {
              "$type": "localizationPersistenceSubtitleEntry",
              "femaleVariant": "Sure? Gamblin\u0027 with your life as the wager, Babs.",
              "maleVariant": "",
              "stringId": "3347855483062267904"
            },
            {
              "$type": "localizationPersistenceSubtitleEntry",
              "femaleVariant": "Fleein\u0027 together – now tha\u0027ss a shot in the dark, V. Gonna lay low, cover our rear. Things cool off, we gonna think next steps, yeah?",
              "maleVariant": "",
              "stringId": "3347856058436890624"
            },
            {
              "$type": "localizationPersistenceSubtitleEntry",
              "femaleVariant": "Yeah, but it\u0027s gonna be even more sus if we both vanish. I\u0027ll stay behind, keep my fingers on the pulse, least till emotions cool, yeah?",
              "maleVariant": "",
              "stringId": "3347857640780017664"
            },
            {
              "$type": "localizationPersistenceSubtitleEntry",
              "femaleVariant": "Shit, Babs… Like… Yeah, OK.",
              "maleVariant": "",
              "stringId": "3347858718766477312"
            },
            {
              "$type": "localizationPersistenceSubtitleEntry",
              "femaleVariant": "Yeah, Yuri prolly grabbed some on the side, wantin\u0027 to hawk \u0027em off for a quick eddie after the scav shitshow.",
              "maleVariant": "",
              "stringId": "3356523669123051520"
            },
            {
              "$type": "localizationPersistenceSubtitleEntry",
              "femaleVariant": "Earth to V?",
              "maleVariant": "",
              "stringId": "3357294654294233096"
            },
            {
              "$type": "localizationPersistenceSubtitleEntry",
              "femaleVariant": "Deep Dive hit too hard, V?",
              "maleVariant": "",
              "stringId": "3357305996212342792"
            },
            {
              "$type": "localizationPersistenceSubtitleEntry",
              "femaleVariant": "Colonel never runs from a fight. Maybe he was gunnin\u0027 to outflank?",
              "maleVariant": "",
              "stringId": "3368173516595040256"
            },
            {
              "$type": "localizationPersistenceSubtitleEntry",
              "femaleVariant": "I\u0027ll figure something out.",
              "maleVariant": "",
              "stringId": "3370864874485092356"
            },
            {
              "$type": "localizationPersistenceSubtitleEntry",
              "femaleVariant": "[Drink] Down the hatch.",
              "maleVariant": "",
              "stringId": "3373734797297135620"
            },
            {
              "$type": "localizationPersistenceSubtitleEntry",
              "femaleVariant": "Down the hatch.",
              "maleVariant": "",
              "stringId": "3373734937739210752"
            },
            {
              "$type": "localizationPersistenceSubtitleEntry",
              "femaleVariant": "Amen to that… Sendin\u0027 ya contact detes. Y\u0027know, just in case.",
              "maleVariant": "",
              "stringId": "3373786837469704192"
            },
            {
              "$type": "localizationPersistenceSubtitleEntry",
              "femaleVariant": "\u003Cmothertongue l=\u0022mex\u0022 m=\u0022¡Virgencita, no mames! ¡Está muerta!\u0022 b=\u0022V…? V! Oh shit, Dive fried her brain! \u0022 a=\u0022\u0022/\u003E",
              "maleVariant": "\u003Cmothertongue l=\u0022mex\u0022 m=\u0022¡Virgencita, no mames! ¡Está muerto!\u0022 b=\u0022V…? V! Oh shit, Dive fried his brain! \u0022 a=\u0022\u0022/\u003E",
              "stringId": "3375249664642461696"
            },
            {
              "$type": "localizationPersistenceSubtitleEntry",
              "femaleVariant": "Rats\u0027ve blocked the road…!",
              "maleVariant": "",
              "stringId": "3446782036059525120"
            },
            {
              "$type": "localizationPersistenceSubtitleEntry",
              "femaleVariant": "We have a groaner, still breathing! He\u0027s sure to tell us something interesting...!",
              "maleVariant": "",
              "stringId": "3446792912074346496"
            },
            {
              "$type": "localizationPersistenceSubtitleEntry",
              "femaleVariant": "See, my shit\u0027s always gotta go tits around the bend, know what\u0027m sayin\u0027?",
              "maleVariant": "",
              "stringId": "3446846264929849344"
            },
            {
              "$type": "localizationPersistenceSubtitleEntry",
              "femaleVariant": "\u0027S like talkin\u0027 to a kid sometimes. \u0027S like he thinks it\u0027s a game, can only get pretend shot.",
              "maleVariant": "",
              "stringId": "3446847270925275136"
            },
            {
              "$type": "localizationPersistenceSubtitleEntry",
              "femaleVariant": "And guess what! I could spend eddies from generators on drugs and joytoys, but I think \u0022be smart, Paco\u0022! So I buy a new wheels, like, preem grade! Let\u0027s take \u0027em and delta!",
              "maleVariant": "",
              "stringId": "3455700771067564032"
            },
            {
              "$type": "localizationPersistenceSubtitleEntry",
              "femaleVariant": "You will not get away with this!",
              "maleVariant": "",
              "stringId": "3672540690312933376"
            },
            {
              "$type": "localizationPersistenceSubtitleEntry",
              "femaleVariant": "Uh-huh. Got it.",
              "maleVariant": "",
              "stringId": "3823184534342807552"
            },
            {
              "$type": "localizationPersistenceSubtitleEntry",
              "femaleVariant": "Fuck. I don\u0027t believe it.",
              "maleVariant": "",
              "stringId": "3823247323291791360"
            },
            {
              "$type": "localizationPersistenceSubtitleEntry",
              "femaleVariant": "Mhm.",
              "maleVariant": "",
              "stringId": "3823275858601521152"
            }
          ]
        }
      }
    },
    "EmbeddedFiles": []
  }
}