{
    "Header": {
        "WolvenKitVersion": "8.10.0",
        "WKitJsonVersion": "0.0.8",
        "GameVersion": 1630,
        "ExportedDateTime": "2023-09-25T02:54:19.6854554Z",
        "DataType": "CR2W",
        "ArchiveFileName": "D:\\2023\\Tháng 9\\CP0277\\TheRedTeam\\source\\archive\\en-us\\subtitles\\open_world\\voicesets\\gang_scv_f_06_enus_30.json"
    },
    "Data": {
        "Version": 195,
        "BuildVersion": 0,
        "RootChunk": {
            "$type": "JsonResource",
            "cookingPlatform": "PLATFORM_PC",
            "root": {
                "HandleId": "0",
                "Data": {
                    "$type": "localizationPersistenceSubtitleEntries",
                    "entries": [
                        {
                            "$type": "localizationPersistenceSubtitleEntry",
                            "femaleVariant": "Tại sao không để tao một mình, hả?",
                            "maleVariant": "Tại sao không để tao một mình, hả?",
                            "stringId": "1898364208004325380"
                        },
                        {
                            "$type": "localizationPersistenceSubtitleEntry",
                            "femaleVariant": "Mmmm…. Vui rồi đấy.",
                            "maleVariant": "Mmmm…. Vui rồi đấy.",
                            "stringId": "1898364208021102596"
                        },
                        {
                            "$type": "localizationPersistenceSubtitleEntry",
                            "femaleVariant": "Cút mẹ mày đi.",
                            "maleVariant": "Cút mẹ mày đi.",
                            "stringId": "1898364208071434244"
                        },
                        {
                            "$type": "localizationPersistenceSubtitleEntry",
                            "femaleVariant": "Cút khỏi đây!",
                            "maleVariant": "Cút khỏi đây!",
                            "stringId": "1898364208088211460"
                        },
                        {
                            "$type": "localizationPersistenceSubtitleEntry",
                            "femaleVariant": "Ngứa tay hả?! Đây, để tao bắn chúng cho.",
                            "maleVariant": "Ngứa tay hả?! Đây, để tao bắn chúng cho.",
                            "stringId": "1898364208155320324"
                        },
                        {
                            "$type": "localizationPersistenceSubtitleEntry",
                            "femaleVariant": "Cuối cùng mày cũng xong đời, phải không?",
                            "maleVariant": "Cuối cùng mày cũng xong đời, phải không?",
                            "stringId": "1898364208172097540"
                        },
                        {
                            "$type": "localizationPersistenceSubtitleEntry",
                            "femaleVariant": "Tao sẽ cho mày biết tay.",
                            "maleVariant": "Tao sẽ cho mày biết tay.",
                            "stringId": "1898364208222429188"
                        },
                        {
                            "$type": "localizationPersistenceSubtitleEntry",
                            "femaleVariant": "Tao đang nói với mày đó!",
                            "maleVariant": "Tao đang nói với mày đó!",
                            "stringId": "1898364208239206404"
                        },
                        {
                            "$type": "localizationPersistenceSubtitleEntry",
                            "femaleVariant": "Đúng rồi, chó cái!",
                            "maleVariant": "Đúng rồi, thằng chó!",
                            "stringId": "1898364208289538052"
                        },
                        {
                            "$type": "localizationPersistenceSubtitleEntry",
                            "femaleVariant": "Hẹn gặp lại sau!",
                            "maleVariant": "Hẹn gặp lại sau!",
                            "stringId": "1898364208306315268"
                        },
                        {
                            "$type": "localizationPersistenceSubtitleEntry",
                            "femaleVariant": "Huh?",
                            "maleVariant": "",
                            "stringId": "1898364208373424132"
                        },
                        {
                            "$type": "localizationPersistenceSubtitleEntry",
                            "femaleVariant": "Hừm.",
                            "maleVariant": "Hừm.",
                            "stringId": "1898364208406978564"
                        },
                        {
                            "$type": "localizationPersistenceSubtitleEntry",
                            "femaleVariant": "Giờ chơi đã hết.",
                            "maleVariant": "Giờ chơi đã hết.",
                            "stringId": "1898364208440532996"
                        },
                        {
                            "$type": "localizationPersistenceSubtitleEntry",
                            "femaleVariant": "Thế là đủ rồi.",
                            "maleVariant": "Thế là đủ rồi.",
                            "stringId": "1898364208457310212"
                        },
                        {
                            "$type": "localizationPersistenceSubtitleEntry",
                            "femaleVariant": "Đầu tiên tao móc mắt mày, nghe chưa?!",
                            "maleVariant": "Đầu tiên tao móc mắt mày, nghe chưa?!",
                            "stringId": "1898364208507641860"
                        },
                        {
                            "$type": "localizationPersistenceSubtitleEntry",
                            "femaleVariant": "Bọn tao sẽ tìm thấy mày, và bọn tao sẽ cắt mày ra thành từng mảnh!",
                            "maleVariant": "Bọn tao sẽ tìm thấy mày, và bọn tao sẽ cắt mày ra thành từng mảnh!",
                            "stringId": "1898364208524419076"
                        },
                        {
                            "$type": "localizationPersistenceSubtitleEntry",
                            "femaleVariant": "Mẹ kiếp! Có xác!",
                            "maleVariant": "Mẹ kiếp! Có xác!",
                            "stringId": "1898364208557973508"
                        },
                        {
                            "$type": "localizationPersistenceSubtitleEntry",
                            "femaleVariant": "Ừ. Ừ.",
                            "maleVariant": "Ừ. Ừ.",
                            "stringId": "1898364208591527940"
                        },
                        {
                            "$type": "localizationPersistenceSubtitleEntry",
                            "femaleVariant": "Mày bị điên hay gì vậy?!",
                            "maleVariant": "Mày bị điên hay gì vậy?!",
                            "stringId": "1898364208625082372"
                        },
                        {
                            "$type": "localizationPersistenceSubtitleEntry",
                            "femaleVariant": "Có vài thằng khốn sau đít tao!",
                            "maleVariant": "Có vài thằng khốn sau đít tao!",
                            "stringId": "1898364208658636804"
                        },
                        {
                            "$type": "localizationPersistenceSubtitleEntry",
                            "femaleVariant": "Nói lời tạm biệt đi!",
                            "maleVariant": "Nói lời tạm biệt đi!",
                            "stringId": "1898364208708968452"
                        },
                        {
                            "$type": "localizationPersistenceSubtitleEntry",
                            "femaleVariant": "Arghhh!",
                            "maleVariant": "",
                            "stringId": "1898364208759300100"
                        },
                        {
                            "$type": "localizationPersistenceSubtitleEntry",
                            "femaleVariant": "Để tao giết mày!",
                            "maleVariant": "Để tao giết mày!",
                            "stringId": "1898364208776077316"
                        },
                        {
                            "$type": "localizationPersistenceSubtitleEntry",
                            "femaleVariant": "Tao cũng không muốn!",
                            "maleVariant": "Tao cũng không muốn!",
                            "stringId": "1898364208826408964"
                        },
                        {
                            "$type": "localizationPersistenceSubtitleEntry",
                            "femaleVariant": "Cứu với! Làm ơn! Cứuuuu!",
                            "maleVariant": "Cứu với! Làm ơn! Cứuuuu!",
                            "stringId": "1898364208843186180"
                        },
                        {
                            "$type": "localizationPersistenceSubtitleEntry",
                            "femaleVariant": "Cẩn thận đấy, cô gái!",
                            "maleVariant": "Cẩn thận đấy, chàng trai!",
                            "stringId": "1898364208893517828"
                        },
                        {
                            "$type": "localizationPersistenceSubtitleEntry",
                            "femaleVariant": "Mày muốn tao tệ đến thế hả? Ha, ha, ha",
                            "maleVariant": "Mày muốn tao tệ đến thế hả? Ha, ha, ha",
                            "stringId": "1898364208910295044"
                        },
                        {
                            "$type": "localizationPersistenceSubtitleEntry",
                            "femaleVariant": "Hoan nghênh chào đón!",
                            "maleVariant": "Hoan nghênh chào đón!",
                            "stringId": "1898364208960626692"
                        },
                        {
                            "$type": "localizationPersistenceSubtitleEntry",
                            "femaleVariant": "Uh-huh… Ừ, cơ bả vai - mày muốn bao nhiêu…? Mày có chắc chỉ muốn hệ giằng thôi chứ?",
                            "maleVariant": "Uh-huh… Ừ, cơ bả vai - mày muốn bao nhiêu…? Mày có chắc chỉ muốn hệ giằng thôi chứ?",
                            "stringId": "1898364209010958340"
                        },
                        {
                            "$type": "localizationPersistenceSubtitleEntry",
                            "femaleVariant": "Không… Ông Jockboy đã chơi cả thị trấn rồi… Ừ, ông ấy có rất nhiều người hâm mộ, ha ha ha.",
                            "maleVariant": "Không… Ông Jockboy đã chơi cả thị trấn rồi… Ừ, ông ấy có rất nhiều người hâm mộ, ha ha ha.",
                            "stringId": "1898364209027735556"
                        },
                        {
                            "$type": "localizationPersistenceSubtitleEntry",
                            "femaleVariant": "Ở bên nhau! Đừng tách lẻ!",
                            "maleVariant": "Ở bên nhau! Đừng tách lẻ!",
                            "stringId": "1898364209078067204"
                        },
                        {
                            "$type": "localizationPersistenceSubtitleEntry",
                            "femaleVariant": "Còn gì nữa không?! Mẹ kiếp!",
                            "maleVariant": "Còn gì nữa không?! Mẹ kiếp!",
                            "stringId": "1898364209111621636"
                        },
                        {
                            "$type": "localizationPersistenceSubtitleEntry",
                            "femaleVariant": "Lựu đạn!",
                            "maleVariant": "Lựu đạn!",
                            "stringId": "1898364209145176068"
                        },
                        {
                            "$type": "localizationPersistenceSubtitleEntry",
                            "femaleVariant": "Gặp lại sau.",
                            "maleVariant": "Gặp lại sau.",
                            "stringId": "1898364209161953284"
                        },
                        {
                            "$type": "localizationPersistenceSubtitleEntry",
                            "femaleVariant": "Tao không thích thế này chút nào.",
                            "maleVariant": "Tao không thích thế này chút nào.",
                            "stringId": "1898364209178730500"
                        },
                        {
                            "$type": "localizationPersistenceSubtitleEntry",
                            "femaleVariant": "Hả? Tốt hơn nên đi kiểm tra.",
                            "maleVariant": "Hả? Tốt hơn nên đi kiểm tra.",
                            "stringId": "1898364209245839364"
                        },
                        {
                            "$type": "localizationPersistenceSubtitleEntry",
                            "femaleVariant": "Ồ vãi cứt! Có thứ gì đó rớt xuống.",
                            "maleVariant": "Ồ vãi cứt! Có thứ gì đó rớt xuống.",
                            "stringId": "1898364209262616580"
                        },
                        {
                            "$type": "localizationPersistenceSubtitleEntry",
                            "femaleVariant": "Đi tiếp đi! Tao tóm được mày rồi.",
                            "maleVariant": "Đi tiếp đi! Tao tóm được mày rồi.",
                            "stringId": "1898364209296171012"
                        },
                        {
                            "$type": "localizationPersistenceSubtitleEntry",
                            "femaleVariant": "Nó là của tao!",
                            "maleVariant": "Nó là của tao!",
                            "stringId": "1898364209312948228"
                        },
                        {
                            "$type": "localizationPersistenceSubtitleEntry",
                            "femaleVariant": "Ekhhh... Ekkhhh... con khốn... arghh...",
                            "maleVariant": "Ekhhh... Ekkhhh... thằng khốn... arghh...",
                            "stringId": "1898364209346502660"
                        },
                        {
                            "$type": "localizationPersistenceSubtitleEntry",
                            "femaleVariant": "Tao có bắp tay với giá tốt… Yeah, chúng ta có thể nói chuyện… Yeah.",
                            "maleVariant": "Tao có bắp tay với giá tốt… Yeah, chúng ta có thể nói chuyện… Yeah.",
                            "stringId": "1898374185783779328"
                        },
                        {
                            "$type": "localizationPersistenceSubtitleEntry",
                            "femaleVariant": "Còn cơ bắp - chúng ta đang nói về chất tăng cường nào vậy? Graphen hả…? Có người rất hiểu biết chuyện này, ha ha ha… Yeah, yeah.",
                            "maleVariant": "Còn cơ bắp - chúng ta đang nói về chất tăng cường nào vậy? Graphen hả…? Có người rất hiểu biết chuyện này, ha ha ha… Yeah, yeah.",
                            "stringId": "1898374446417829888"
                        },
                        {
                            "$type": "localizationPersistenceSubtitleEntry",
                            "femaleVariant": "Chết tiệt!",
                            "maleVariant": "Chết tiệt!",
                            "stringId": "2232129797764554752"
                        },
                        {
                            "$type": "localizationPersistenceSubtitleEntry",
                            "femaleVariant": "Không ổn rồi!",
                            "maleVariant": "Không ổn rồi!",
                            "stringId": "2232129798049767428"
                        },
                        {
                            "$type": "localizationPersistenceSubtitleEntry",
                            "femaleVariant": "Cái quái gì vừa xảy ra vậy...?!",
                            "maleVariant": "Cái quái gì vừa xảy ra vậy...?!",
                            "stringId": "2232129798100099076"
                        },
                        {
                            "$type": "localizationPersistenceSubtitleEntry",
                            "femaleVariant": "Không gọi ai cả, chơi luôn.",
                            "maleVariant": "Không gọi ai cả, chơi luôn.",
                            "stringId": "2232129798267871236"
                        },
                        {
                            "$type": "localizationPersistenceSubtitleEntry",
                            "femaleVariant": "Mày sẽ không thoát khỏi đó đâu!",
                            "maleVariant": "Mày sẽ không thoát khỏi đó đâu!",
                            "stringId": "2232129798603415556"
                        },
                        {
                            "$type": "localizationPersistenceSubtitleEntry",
                            "femaleVariant": "Nghĩ tao sợ mày à?!",
                            "maleVariant": "Nghĩ tao sợ mày à?!",
                            "stringId": "2232129798720856068"
                        },
                        {
                            "$type": "localizationPersistenceSubtitleEntry",
                            "femaleVariant": "Nào! Tao ở ngay đây!",
                            "maleVariant": "Nào! Tao ở ngay đây!",
                            "stringId": "2232129798821519360"
                        },
                        {
                            "$type": "localizationPersistenceSubtitleEntry",
                            "femaleVariant": "Đây là cách chúng ta làm điều đó!",
                            "maleVariant": "Đây là cách chúng ta làm điều đó!",
                            "stringId": "2232129799039623172"
                        },
                        {
                            "$type": "localizationPersistenceSubtitleEntry",
                            "femaleVariant": "Ôi! Chắc đau đấy!",
                            "maleVariant": "Ôi! Chắc đau đấy!",
                            "stringId": "2232129799391944704"
                        },
                        {
                            "$type": "localizationPersistenceSubtitleEntry",
                            "femaleVariant": "Nó gần chết rồi! Tiếp tục đi! Haha!",
                            "maleVariant": "Nó gần chết rồi! Tiếp tục đi! Haha!",
                            "stringId": "2232129799995924484"
                        },
                        {
                            "$type": "localizationPersistenceSubtitleEntry",
                            "femaleVariant": "Ồ, còn kìa!",
                            "maleVariant": "Ồ, còn kìa!",
                            "stringId": "2232129800130142212"
                        },
                        {
                            "$type": "localizationPersistenceSubtitleEntry",
                            "femaleVariant": "Trốn cũng đéo giúp được gì đâu!",
                            "maleVariant": "Trốn cũng đéo giúp được gì đâu!",
                            "stringId": "2232129800247582724"
                        },
                        {
                            "$type": "localizationPersistenceSubtitleEntry",
                            "femaleVariant": "Đang nạp đạn!",
                            "maleVariant": "Đang nạp đạn!",
                            "stringId": "2232129800365023236"
                        },
                        {
                            "$type": "localizationPersistenceSubtitleEntry",
                            "femaleVariant": "Mẹ kiếp?! Mày ngu hả?!",
                            "maleVariant": "Mẹ kiếp?! Mày ngu hả?!",
                            "stringId": "2232129800499240964"
                        },
                        {
                            "$type": "localizationPersistenceSubtitleEntry",
                            "femaleVariant": "Không thấy gì hết! Cứu với!",
                            "maleVariant": "Không thấy gì hết! Cứu với!",
                            "stringId": "2232129800750899200"
                        },
                        {
                            "$type": "localizationPersistenceSubtitleEntry",
                            "femaleVariant": "Con lồn lắm trò!",
                            "maleVariant": "Thằng lồn lắm trò!",
                            "stringId": "2232129800885116932"
                        },
                        {
                            "$type": "localizationPersistenceSubtitleEntry",
                            "femaleVariant": "Ồ! Tiệc tùng đi nào! Ha ha!",
                            "maleVariant": "Ồ! Tiệc tùng đi nào! Ha ha!",
                            "stringId": "2232129801019334660"
                        },
                        {
                            "$type": "localizationPersistenceSubtitleEntry",
                            "femaleVariant": "Cần thêm súng nữa!",
                            "maleVariant": "Cần thêm súng nữa!",
                            "stringId": "2232129801153552388"
                        },
                        {
                            "$type": "localizationPersistenceSubtitleEntry",
                            "femaleVariant": "Mày xong đời rồi!",
                            "maleVariant": "Mày xong đời rồi!",
                            "stringId": "2232129801321324548"
                        },
                        {
                            "$type": "localizationPersistenceSubtitleEntry",
                            "femaleVariant": "Đang ném!",
                            "maleVariant": "Đang ném!",
                            "stringId": "2232129801455542276"
                        },
                        {
                            "$type": "localizationPersistenceSubtitleEntry",
                            "femaleVariant": "Coi chừng! Tới rồi!",
                            "maleVariant": "Coi chừng! Tới rồi!",
                            "stringId": "2232129801572982788"
                        },
                        {
                            "$type": "localizationPersistenceSubtitleEntry",
                            "femaleVariant": "Aaaaaarggh! Dừng lại! Dừng lại!",
                            "maleVariant": "Aaaaaarggh! Dừng lại! Dừng lại!",
                            "stringId": "2232129801690423300"
                        }
                    ]
                }
            }
        },
        "EmbeddedFiles": []
    }
}