{
    "Header": {
        "WolvenKitVersion": "8.10.0",
        "WKitJsonVersion": "0.0.8",
        "GameVersion": 1630,
        "ExportedDateTime": "2023-09-25T02:54:23.8695497Z",
        "DataType": "CR2W",
        "ArchiveFileName": "D:\\2023\\Tháng 9\\CP0277\\TheRedTeam\\source\\archive\\en-us\\subtitles\\quest\\mq000\\mq000_01_apartment.json"
    },
    "Data": {
        "Version": 195,
        "BuildVersion": 0,
        "RootChunk": {
            "$type": "JsonResource",
            "cookingPlatform": "PLATFORM_PC",
            "root": {
                "HandleId": "0",
                "Data": {
                    "$type": "localizationPersistenceSubtitleEntries",
                    "entries": [
                        {
                            "$type": "localizationPersistenceSubtitleEntry",
                            "femaleVariant": "[Đi ngủ]",
                            "maleVariant": "[Đi ngủ]",
                            "stringId": "2028698177566056448"
                        },
                        {
                            "$type": "localizationPersistenceSubtitleEntry",
                            "femaleVariant": "[Đứng dậy]",
                            "maleVariant": "[Đứng dậy]",
                            "stringId": "2028699165173653504"
                        },
                        {
                            "$type": "localizationPersistenceSubtitleEntry",
                            "femaleVariant": "[Đi tắm]",
                            "maleVariant": "[Đi tắm]",
                            "stringId": "2028737051734482948"
                        },
                        {
                            "$type": "localizationPersistenceSubtitleEntry",
                            "femaleVariant": "[Ra ngoài]",
                            "maleVariant": "[Ra ngoài]",
                            "stringId": "2078186557357858816"
                        },
                        {
                            "$type": "localizationPersistenceSubtitleEntry",
                            "femaleVariant": "[Nhìn vào gương]",
                            "maleVariant": "[Nhìn vào gương]",
                            "stringId": "2086887489105780736"
                        },
                        {
                            "$type": "localizationPersistenceSubtitleEntry",
                            "femaleVariant": "[Ngừng nhìn]",
                            "maleVariant": "[Ngừng nhìn]",
                            "stringId": "2086931518929461248"
                        },
                        {
                            "$type": "localizationPersistenceSubtitleEntry",
                            "femaleVariant": "[Mở TV]",
                            "maleVariant": "[Mở TV]",
                            "stringId": "2123159550320091136"
                        },
                        {
                            "$type": "localizationPersistenceSubtitleEntry",
                            "femaleVariant": "[Chuyển kênh tiếp theo]",
                            "maleVariant": "[Chuyển kênh tiếp theo]",
                            "stringId": "2318488737380474884"
                        },
                        {
                            "$type": "localizationPersistenceSubtitleEntry",
                            "femaleVariant": "[Chuyển kênh trước đó]",
                            "maleVariant": "[Chuyển kênh trước đó]",
                            "stringId": "2318489634374328320"
                        },
                        {
                            "$type": "localizationPersistenceSubtitleEntry",
                            "femaleVariant": "[Tắt]",
                            "maleVariant": "[Tắt]",
                            "stringId": "2318490007398948864"
                        },
                        {
                            "$type": "localizationPersistenceSubtitleEntry",
                            "femaleVariant": "[Cười]",
                            "maleVariant": "[Cười]",
                            "stringId": "2531839124031037440"
                        },
                        {
                            "$type": "localizationPersistenceSubtitleEntry",
                            "femaleVariant": "[Cau có]",
                            "maleVariant": "[Cau có]",
                            "stringId": "2531839124031037460"
                        },
                        {
                            "$type": "localizationPersistenceSubtitleEntry",
                            "femaleVariant": "[Bĩu môi]",
                            "maleVariant": "[Bĩu môi]",
                            "stringId": "2531839124031037480"
                        },
                        {
                            "$type": "localizationPersistenceSubtitleEntry",
                            "femaleVariant": "[Rụt rè]",
                            "maleVariant": "[Rụt rè]",
                            "stringId": "2531839124047814664"
                        },
                        {
                            "$type": "localizationPersistenceSubtitleEntry",
                            "femaleVariant": "[Nhìn chằm chằm]",
                            "maleVariant": "[Nhìn chằm chằm]",
                            "stringId": "2531839124047814684"
                        },
                        {
                            "$type": "localizationPersistenceSubtitleEntry",
                            "femaleVariant": "[Thay đổi ngoại hình]",
                            "maleVariant": "[Thay đổi ngoại hình]",
                            "stringId": "2850426924185837568"
                        },
                        {
                            "$type": "localizationPersistenceSubtitleEntry",
                            "femaleVariant": "[Thay đổi khuôn mặt]",
                            "maleVariant": "[Thay đổi khuôn mặt]",
                            "stringId": "2851650094028972032"
                        },
                        {
                            "$type": "localizationPersistenceSubtitleEntry",
                            "femaleVariant": "[Trở về]",
                            "maleVariant": "[Trở về]",
                            "stringId": "2851670434205556736"
                        },
                        {
                            "$type": "localizationPersistenceSubtitleEntry",
                            "femaleVariant": "[Mở Tủ Quần Áo]",
                            "maleVariant": "[Mở Tủ Quần Áo]",
                            "stringId": "3357958381927030788"
                        }
                    ]
                }
            }
        },
        "EmbeddedFiles": []
    }
}