{
  "Header": {
    "WolvenKitVersion": "8.10.0",
    "WKitJsonVersion": "0.0.8",
    "GameVersion": 1630,
    "ExportedDateTime": "2023-09-25T02:54:07.5457744Z",
    "DataType": "CR2W",
    "ArchiveFileName": "D:\\2023\\Tháng 9\\CP0277\\TheRedTeam\\source\\archive\\en-us\\subtitles\\open_world\\scenes\\wat_nid_chat_018.json"
  },
  "Data": {
    "Version": 195,
    "BuildVersion": 0,
    "RootChunk": {
      "$type": "JsonResource",
      "cookingPlatform": "PLATFORM_PC",
      "root": {
        "HandleId": "0",
        "Data": {
          "$type": "localizationPersistenceSubtitleEntries",
          "entries": [
            {
              "$type": "localizationPersistenceSubtitleEntry",
              "femaleVariant": "Everything go to the club?",
              "maleVariant": "",
              "stringId": "2156409163642036224"
            },
            {
              "$type": "localizationPersistenceSubtitleEntry",
              "femaleVariant": "Mhm. And to All Foods. Nothin\u0027 left.",
              "maleVariant": "",
              "stringId": "2230325338355515392"
            },
            {
              "$type": "localizationPersistenceSubtitleEntry",
              "femaleVariant": "Cunts coulda spared us a little... One whiff and I\u0027m overclockin\u0027, negative latency, pure fuckin\u0027 chrome-synaptic symbiosis.",
              "maleVariant": "",
              "stringId": "2230325534581833728"
            },
            {
              "$type": "localizationPersistenceSubtitleEntry",
              "femaleVariant": "It\u0027s like CHOOH2. You fill \u0027er up, lead-foot the pedal, and it\u0027s no brakes, no fucks given.",
              "maleVariant": "",
              "stringId": "2230325648398467072"
            },
            {
              "$type": "localizationPersistenceSubtitleEntry",
              "femaleVariant": "Bullshit. Maybe you don\u0027t get tired, but you\u0027re still noided.",
              "maleVariant": "",
              "stringId": "2230325781005582336"
            },
            {
              "$type": "localizationPersistenceSubtitleEntry",
              "femaleVariant": "Take a little too much and your sensory dampers fly out the window. You\u0027re just there – quiverin\u0027 like a bag o\u0027 raw meat.",
              "maleVariant": "",
              "stringId": "2230325879018078208"
            },
            {
              "$type": "localizationPersistenceSubtitleEntry",
              "femaleVariant": "Ah, but see, there\u0027s a way around everythin\u0027 – for that you just gotta swap out your amygdala.",
              "maleVariant": "",
              "stringId": "2230326000048914432"
            },
            {
              "$type": "localizationPersistenceSubtitleEntry",
              "femaleVariant": "Hm, never heard o\u0027 that. Might give it a whirl.",
              "maleVariant": "",
              "stringId": "2230326116029808640"
            }
          ]
        }
      }
    },
    "EmbeddedFiles": []
  }
}